jsonl_resumable/__init__.py
jsonl_resumable/index.py
jsonl_resumable/models.py
jsonl_resumable/persistence.py
jsonl_resumable-0.2.0.dist-info/METADATA
jsonl_resumable-0.2.0.dist-info/WHEEL
jsonl_resumable-0.2.0.dist-info/licenses/LICENSE
jsonl_resumable-0.2.0.dist-info/RECORD
