Metadata-Version: 2.4
Name: jsonl-resumable
Version: 0.2.0
Summary: O(1) resume for large JSONL streams via byte-offset indexing
Project-URL: Homepage, https://github.com/pranavtotla/jsonl-resumable
Project-URL: Repository, https://github.com/pranavtotla/jsonl-resumable
Project-URL: Issues, https://github.com/pranavtotla/jsonl-resumable/issues
Author-email: Pranav <pranav@snaptrude.com>
License-Expression: MIT
License-File: LICENSE
Keywords: etl,index,jsonl,llm,resume,seek,streaming
Classifier: Development Status :: 4 - Beta
Classifier: Intended Audience :: Developers
Classifier: License :: OSI Approved :: MIT License
Classifier: Programming Language :: Python :: 3
Classifier: Programming Language :: Python :: 3.10
Classifier: Programming Language :: Python :: 3.11
Classifier: Programming Language :: Python :: 3.12
Classifier: Topic :: Software Development :: Libraries :: Python Modules
Classifier: Topic :: Text Processing
Classifier: Typing :: Typed
Requires-Python: >=3.10
Provides-Extra: dev
Requires-Dist: mypy>=1.0; extra == 'dev'
Requires-Dist: pytest-cov>=4.0; extra == 'dev'
Requires-Dist: pytest>=7.0; extra == 'dev'
Requires-Dist: ruff>=0.1; extra == 'dev'
